autonomous_business/__init__.py
autonomous_business/echo.py
autonomous_business/py.typed
autonomous_business/utils/__init__.py
autonomous_business/utils/pdf2text.py
autonomous_business-0.1.0a2.dist-info/WHEEL
autonomous_business-0.1.0a2.dist-info/METADATA
autonomous_business-0.1.0a2.dist-info/RECORD
