Metadata-Version: 2.3
Name: autonomous-business
Version: 0.1.0a2
Summary: Autonomous business system based on paper https://doi.org/10.1109/ACCESS.2025.3583260
Author: Cecil Pang, Ying Kang
Author-email: Cecil Pang <cpang2@binghamton.edu>, Ying Kang <happykygo@gmail.com>
Requires-Dist: bs4>=0.0.2
Requires-Dist: httpx>=0.28.1
Requires-Dist: mcp[cli]>=1.12.0
Requires-Dist: openai-agents>=0.2.2
Requires-Dist: pymupdf>=1.26.3
Requires-Dist: python-dotenv>=1.1.1
Requires-Python: >=3.12
